loraclip/__init__.py
loraclip/lora_clip.py
loraclip/model.py
loraclip/loralib/__init__.py
loraclip/loralib/layers.py
loraclip/loralib/utils.py
loraclip-0.1.0.dist-info/LICENSE
loraclip-0.1.0.dist-info/METADATA
loraclip-0.1.0.dist-info/WHEEL
loraclip-0.1.0.dist-info/top_level.txt
loraclip-0.1.0.dist-info/RECORD
