Metadata-Version: 2.1
Name: loraclip
Version: 0.1.0
Summary: A simple and efficient wrapper for LoRA-ifying CLIP.
Home-page: https://github.com/jaisidhsingh/LoRA-CLIP
Author: Jaisidh Singh
Author-email: jaisidhsingh@gmail.com
License: UNKNOWN
Platform: UNKNOWN
Classifier: Programming Language :: Python :: 3
Classifier: License :: OSI Approved :: MIT License
Classifier: Operating System :: OS Independent
Requires-Python: >=3.6
Requires-Dist: numpy
Requires-Dist: torch
Requires-Dist: ftfy
Requires-Dist: regex
